{"cameraMode":{"drawMode":0,"name":"Shaded","section":"Shading Mode"},"sceneLighting":true,"audioPlay":false,"sceneViewState":{"showFog":true,"showMaterialUpdate":false,"showSkybox":true,"showFlares":true,"showImageEffects":true,"showParticleSystems":true},"in2DMode":false,"pivot":{"x":142.6916961669922,"y":-2.2296342849731447,"z":201.9193115234375},"rotation":{"x":-0.10659752786159516,"y":-0.32727375626564028,"z":0.03632465377449989,"w":-0.9386457800865173},"size":33.39869689941406,"orthographic":false}